havhav/__init__.py
havhav/handler.py
havhav/models.py
havhav-0.1.3.dist-info/WHEEL
havhav-0.1.3.dist-info/METADATA
havhav-0.1.3.dist-info/RECORD
